pyqtgraph_scope_plots/__init__.py
pyqtgraph_scope_plots/animation_plot_table_widget.py
pyqtgraph_scope_plots/code_input_dialog.py
pyqtgraph_scope_plots/color_signals_table.py
pyqtgraph_scope_plots/enum_waveform_plotitem.py
pyqtgraph_scope_plots/filter_signals_table.py
pyqtgraph_scope_plots/graphics_collections.py
pyqtgraph_scope_plots/interactivity_mixins.py
pyqtgraph_scope_plots/legend_plot_widget.py
pyqtgraph_scope_plots/multi_plot_widget.py
pyqtgraph_scope_plots/plots_table_widget.py
pyqtgraph_scope_plots/py.typed
pyqtgraph_scope_plots/recents.py
pyqtgraph_scope_plots/search_signals_table.py
pyqtgraph_scope_plots/signals_table.py
pyqtgraph_scope_plots/stats_signals_table.py
pyqtgraph_scope_plots/time_axis.py
pyqtgraph_scope_plots/timeshift_signals_table.py
pyqtgraph_scope_plots/transforms_signal_table.py
pyqtgraph_scope_plots/visibility_toggle_table.py
pyqtgraph_scope_plots/xy_plot.py
pyqtgraph_scope_plots/xy_plot_legends.py
pyqtgraph_scope_plots/xy_plot_refgeo.py
pyqtgraph_scope_plots/xy_plot_splitter.py
pyqtgraph_scope_plots/xy_plot_table.py
pyqtgraph_scope_plots/xy_plot_visibility.py
pyqtgraph_scope_plots/csv/__init__.py
pyqtgraph_scope_plots/csv/__main__.py
pyqtgraph_scope_plots/csv/csv_plots.py
pyqtgraph_scope_plots/util/__init__.py
pyqtgraph_scope_plots/util/cache_dict.py
pyqtgraph_scope_plots/util/mixin_cols_table.py
pyqtgraph_scope_plots/util/save_restore_model.py
pyqtgraph_scope_plots/util/util.py
pyqtgraph_scope_plots-1.6.2.dist-info/licenses/LICENSE
pyqtgraph_scope_plots-1.6.2.dist-info/METADATA
pyqtgraph_scope_plots-1.6.2.dist-info/WHEEL
pyqtgraph_scope_plots-1.6.2.dist-info/top_level.txt
pyqtgraph_scope_plots-1.6.2.dist-info/RECORD
