Metadata-Version: 2.4
Name: pyqtgraph-scope-plots
Version: 1.6.2
Summary: Scope like plot utilities for pyqtgraph
Author-email: Richard Lin <richardlin@enphaseenergy.com>
License-Expression: Apache-2.0
Project-URL: Homepage, https://github.com/enphase/pyqtgraph-scope-plots
Project-URL: Issues, https://github.com/enphase/pyqtgraph-scope-plots/issues
Classifier: Programming Language :: Python :: 3
Classifier: Operating System :: OS Independent
Classifier: Topic :: Software Development :: Libraries :: Python Modules
Classifier: Topic :: Scientific/Engineering :: Visualization
Classifier: Topic :: Software Development :: User Interfaces
Requires-Python: ~=3.8
License-File: LICENSE
Requires-Dist: PySide6!=6.9.1,~=6.6
Requires-Dist: pyqtgraph~=0.13
Requires-Dist: pillow>=9.0
Requires-Dist: pandas~=2.0
Requires-Dist: numpy>=1.19
Requires-Dist: pydantic>=2.0
Requires-Dist: simpleeval>=1.0
Requires-Dist: PyYAML>=6.0
Provides-Extra: dev
Requires-Dist: black~=23.3; extra == "dev"
Requires-Dist: isort~=5.9.2; extra == "dev"
Requires-Dist: flake8~=3.9.2; extra == "dev"
Requires-Dist: types-PyYAML; extra == "dev"
Requires-Dist: pytest~=6.2.4; extra == "dev"
Requires-Dist: pytest-qt~=4.4; extra == "dev"
Requires-Dist: pytest-cov~=6.1.1; extra == "dev"
Requires-Dist: pytest-mypy~=0.10; extra == "dev"
Requires-Dist: mypy~=1.15.0; extra == "dev"
Requires-Dist: pandas-stubs; extra == "dev"
Requires-Dist: PySide6-stubs; extra == "dev"
Requires-Dist: flake8-mypy~=17.8.0; extra == "dev"
Requires-Dist: pre-commit~=2.13.0; extra == "dev"
Dynamic: license-file
